{
  "Pri_900": "#001a5c",
  "Pri_800": "#00247E",
  "Pri_700": "#0833A0",
  "Pri_600": "#1546C2",
  "Pri_500": "#2D62EA",
  "Pri_400": "#3A71FF",
  "Pri_300": "#6691FF",
  "Pri_200": "#92B1FF",
  "Pri_100": "#BFD1FF",
  "Pri_50": "#EBF1FF",
  "Gray_900": "#1D1D1D",
  "Gray_800": "#323232",
  "Gray_700": "#505050",
  "Gray_600": "#737373",
  "Gray_500": "#808080",
  "Gray_400": "#AEAEAE",
  "Gray_300": "#CFCFCF",
  "Gray_200": "#CFCFCF",
  "Gray_100": "#F4F4F4",
  "Gray_50": "#FBFBFB",
  "Basic_Black": "#141212",
  "Basic_White": "#FFFFFF",
  "System_Error": "#DF291D",
  "System_Positive": "#1FB881",
  "Text_900": "#1D1D1D",
  "Text_700": "#505050",
  "Text_400": "#AEAEAE",
  "Text_Wh": "#FFFFFF",
  "Text_Hold": "#CFCFCF",
  "Bg_300": "#CFCFCF",
  "Bg_100": "#F4F4F4",
  "Bg_50": "#FBFBFB",
  "Bg_Wh": "#FFFFFF",
  "Bgc_100": "#BFD1FF",
  "Bgc_50": "#EBF1FF",
  "Line_300": "#CFCFCF",
  "Line_200": "#E7E7E7",
  "Dim": "rgba(40, 40, 40, 0.8)",
  "Shadow": "rgba(231, 231, 231, 0.8)"
}
